configurations/sample.yaml
dotifi/__init__.py
dotifi/__main__.py
dotifi/configuration/__init__.py
dotifi/configuration/load.py
dotifi/dotifi.py
dotifi/nifi/__init__.py
dotifi/nifi/connection.py
dotifi/nifi/generate.py
dotifi/publishing/__init__.py
dotifi/publishing/publish.py
dotifi-0.2.1.dist-info/entry_points.txt
dotifi-0.2.1.dist-info/LICENSE
dotifi-0.2.1.dist-info/WHEEL
dotifi-0.2.1.dist-info/METADATA
dotifi-0.2.1.dist-info/RECORD
