Metadata-Version: 2.1
Name: dotifi
Version: 0.2.1
Summary: Generate DOT files and images from Apache Nifi Flows
Home-page: https://github.com/palindromicity/dotifi
License: Apache-2.0
Keywords: nifi,graphviz,pygraphvis,nipyapi
Author: Otto Fowler
Author-email: ottobackwards@gmail.com
Maintainer: palindromicity
Maintainer-email: github.palindromicity@gmail.com
Requires-Python: >=3.7,<4.0
Classifier: License :: OSI Approved :: Apache Software License
Classifier: Programming Language :: Python :: 3
Classifier: Programming Language :: Python :: 3.7
Classifier: Programming Language :: Python :: 3.8
Requires-Dist: confuse (>=1.1.0,<2.0.0)
Requires-Dist: jsonpickle (>=1.4.1,<2.0.0)
Requires-Dist: nipyapi (>=0.14.3,<0.15.0)
Requires-Dist: pygraphviz (>=1.5,<2.0)
Requires-Dist: pyyaml (>=5.3.1,<6.0.0)
Requires-Dist: wheel (>=0.34.2,<0.35.0)
Project-URL: Repository, https://github.com/palindromicity/dotifi
Project-URL: issues, https://github.com/palindromicity/dotifi/issues
